{
  "totale": 202,
  "generato": "2025-12-15T11:32:50.077Z",
  "flashcards": [
    {
      "id": "italiano-1",
      "fronte": "Quando nacque Dante Alighieri?",
      "retro": "1265 a Firenze",
      "materia": "italiano",
      "categoria": "Dante",
      "difficolta": 1,
      "intervallo": 1,
      "ripetizioni": 0,
      "facilita": 2.5,
      "prossimaRevisione": "2025-12-15T11:32:50.070Z"
    },
    {
      "id": "italiano-2",
      "fronte": "Qual è l'opera principale di Dante?",
      "retro": "La Divina Commedia (1321)",
      "materia": "italiano",
      "categoria": "Dante",
      "difficolta": 1,
      "intervallo": 1,
      "ripetizioni": 0,
      "facilita": 2.5,
      "prossimaRevisione": "2025-12-15T11:32:50.070Z"
    },
    {
      "id": "italiano-3",
      "fronte": "Quali sono le tre cantiche della Divina Commedia?",
      "retro": "Inferno, Purgatorio, Paradiso",
      "materia": "italiano",
      "categoria": "Dante",
      "difficolta": 1,
      "intervallo": 1,
      "ripetizioni": 0,
      "facilita": 2.5,
      "prossimaRevisione": "2025-12-15T11:32:50.070Z"
    },
    {
      "id": "italiano-4",
      "fronte": "Chi è Beatrice per Dante?",
      "retro": "La donna amata, guida spirituale nel Paradiso",
      "materia": "italiano",
      "categoria": "Dante",
      "difficolta": 2,
      "intervallo": 1,
      "ripetizioni": 0,
      "facilita": 2.5,
      "prossimaRevisione": "2025-12-15T11:32:50.070Z"
    },
    {
      "id": "italiano-5",
      "fronte": "Cos'è la \"Vita Nova\"?",
      "retro": "Prosimetro dedicato a Beatrice (1294)",
      "materia": "italiano",
      "categoria": "Dante",
      "difficolta": 2,
      "intervallo": 1,
      "ripetizioni": 0,
      "facilita": 2.5,
      "prossimaRevisione": "2025-12-15T11:32:50.070Z"
    },
    {
      "id": "italiano-6",
      "fronte": "Cosa significa \"Nel mezzo del cammin di nostra vita\"?",
      "retro": "Dante ha 35 anni, metà della vita secondo la Bibbia",
      "materia": "italiano",
      "categoria": "Dante",
      "difficolta": 2,
      "intervallo": 1,
      "ripetizioni": 0,
      "facilita": 2.5,
      "prossimaRevisione": "2025-12-15T11:32:50.070Z"
    },
    {
      "id": "italiano-7",
      "fronte": "Chi guida Dante nell'Inferno?",
      "retro": "Virgilio, simbolo della ragione",
      "materia": "italiano",
      "categoria": "Dante",
      "difficolta": 1,
      "intervallo": 1,
      "ripetizioni": 0,
      "facilita": 2.5,
      "prossimaRevisione": "2025-12-15T11:32:50.070Z"
    },
    {
      "id": "italiano-8",
      "fronte": "Cos'è il \"contrapasso\"?",
      "retro": "Pena che rispecchia per analogia o contrasto il peccato",
      "materia": "italiano",
      "categoria": "Dante",
      "difficolta": 3,
      "intervallo": 1,
      "ripetizioni": 0,
      "facilita": 2.5,
      "prossimaRevisione": "2025-12-15T11:32:50.070Z"
    },
    {
      "id": "italiano-9",
      "fronte": "Quando nacque Francesco Petrarca?",
      "retro": "1304 ad Arezzo",
      "materia": "italiano",
      "categoria": "Petrarca",
      "difficolta": 1,
      "intervallo": 1,
      "ripetizioni": 0,
      "facilita": 2.5,
      "prossimaRevisione": "2025-12-15T11:32:50.070Z"
    },
    {
      "id": "italiano-10",
      "fronte": "Qual è l'opera principale di Petrarca?",
      "retro": "Il Canzoniere (366 componimenti)",
      "materia": "italiano",
      "categoria": "Petrarca",
      "difficolta": 1,
      "intervallo": 1,
      "ripetizioni": 0,
      "facilita": 2.5,
      "prossimaRevisione": "2025-12-15T11:32:50.070Z"
    },
    {
      "id": "italiano-11",
      "fronte": "Chi è Laura per Petrarca?",
      "retro": "La donna amata, vista per la prima volta il 6 aprile 1327",
      "materia": "italiano",
      "categoria": "Petrarca",
      "difficolta": 2,
      "intervallo": 1,
      "ripetizioni": 0,
      "facilita": 2.5,
      "prossimaRevisione": "2025-12-15T11:32:50.070Z"
    },
    {
      "id": "italiano-12",
      "fronte": "Cos'è il \"Secretum\"?",
      "retro": "Dialogo interiore con Sant'Agostino",
      "materia": "italiano",
      "categoria": "Petrarca",
      "difficolta": 2,
      "intervallo": 1,
      "ripetizioni": 0,
      "facilita": 2.5,
      "prossimaRevisione": "2025-12-15T11:32:50.071Z"
    },
    {
      "id": "italiano-13",
      "fronte": "Perché Petrarca è considerato padre dell'Umanesimo?",
      "retro": "Riscoprì i classici latini e pose l'uomo al centro",
      "materia": "italiano",
      "categoria": "Petrarca",
      "difficolta": 3,
      "intervallo": 1,
      "ripetizioni": 0,
      "facilita": 2.5,
      "prossimaRevisione": "2025-12-15T11:32:50.071Z"
    },
    {
      "id": "italiano-14",
      "fronte": "Quando nacque Giovanni Boccaccio?",
      "retro": "1313 a Certaldo",
      "materia": "italiano",
      "categoria": "Boccaccio",
      "difficolta": 1,
      "intervallo": 1,
      "ripetizioni": 0,
      "facilita": 2.5,
      "prossimaRevisione": "2025-12-15T11:32:50.071Z"
    },
    {
      "id": "italiano-15",
      "fronte": "Cos'è il Decameron?",
      "retro": "100 novelle raccontate da 10 giovani in 10 giorni durante la peste",
      "materia": "italiano",
      "categoria": "Boccaccio",
      "difficolta": 1,
      "intervallo": 1,
      "ripetizioni": 0,
      "facilita": 2.5,
      "prossimaRevisione": "2025-12-15T11:32:50.071Z"
    },
    {
      "id": "italiano-16",
      "fronte": "In che anno fu scritto il Decameron?",
      "retro": "1349-1353, dopo la peste nera",
      "materia": "italiano",
      "categoria": "Boccaccio",
      "difficolta": 2,
      "intervallo": 1,
      "ripetizioni": 0,
      "facilita": 2.5,
      "prossimaRevisione": "2025-12-15T11:32:50.071Z"
    },
    {
      "id": "italiano-17",
      "fronte": "Quali sono i temi principali del Decameron?",
      "retro": "Amore, fortuna, ingegno, critica sociale",
      "materia": "italiano",
      "categoria": "Boccaccio",
      "difficolta": 2,
      "intervallo": 1,
      "ripetizioni": 0,
      "facilita": 2.5,
      "prossimaRevisione": "2025-12-15T11:32:50.071Z"
    },
    {
      "id": "italiano-18",
      "fronte": "Quando nacque Niccolò Machiavelli?",
      "retro": "1469 a Firenze",
      "materia": "italiano",
      "categoria": "Machiavelli",
      "difficolta": 1,
      "intervallo": 1,
      "ripetizioni": 0,
      "facilita": 2.5,
      "prossimaRevisione": "2025-12-15T11:32:50.071Z"
    },
    {
      "id": "italiano-19",
      "fronte": "Qual è l'opera principale di Machiavelli?",
      "retro": "Il Principe (1513)",
      "materia": "italiano",
      "categoria": "Machiavelli",
      "difficolta": 1,
      "intervallo": 1,
      "ripetizioni": 0,
      "facilita": 2.5,
      "prossimaRevisione": "2025-12-15T11:32:50.071Z"
    },
    {
      "id": "italiano-20",
      "fronte": "Cosa significa \"il fine giustifica i mezzi\"?",
      "retro": "Il principe deve usare ogni mezzo per mantenere lo stato",
      "materia": "italiano",
      "categoria": "Machiavelli",
      "difficolta": 2,
      "intervallo": 1,
      "ripetizioni": 0,
      "facilita": 2.5,
      "prossimaRevisione": "2025-12-15T11:32:50.071Z"
    },
    {
      "id": "italiano-21",
      "fronte": "Cos'è la \"virtù\" per Machiavelli?",
      "retro": "Capacità politica di dominare la fortuna",
      "materia": "italiano",
      "categoria": "Machiavelli",
      "difficolta": 3,
      "intervallo": 1,
      "ripetizioni": 0,
      "facilita": 2.5,
      "prossimaRevisione": "2025-12-15T11:32:50.071Z"
    },
    {
      "id": "italiano-22",
      "fronte": "Qual è l'opera principale di Ariosto?",
      "retro": "Orlando Furioso (1532)",
      "materia": "italiano",
      "categoria": "Ariosto",
      "difficolta": 1,
      "intervallo": 1,
      "ripetizioni": 0,
      "facilita": 2.5,
      "prossimaRevisione": "2025-12-15T11:32:50.071Z"
    },
    {
      "id": "italiano-23",
      "fronte": "Di cosa parla l'Orlando Furioso?",
      "retro": "Follia d'amore di Orlando, avventure cavalleresche",
      "materia": "italiano",
      "categoria": "Ariosto",
      "difficolta": 2,
      "intervallo": 1,
      "ripetizioni": 0,
      "facilita": 2.5,
      "prossimaRevisione": "2025-12-15T11:32:50.071Z"
    },
    {
      "id": "italiano-24",
      "fronte": "Cos'è l'\"entrelacement\"?",
      "retro": "Tecnica narrativa di intreccio di storie parallele",
      "materia": "italiano",
      "categoria": "Ariosto",
      "difficolta": 3,
      "intervallo": 1,
      "ripetizioni": 0,
      "facilita": 2.5,
      "prossimaRevisione": "2025-12-15T11:32:50.071Z"
    },
    {
      "id": "italiano-25",
      "fronte": "Qual è l'opera principale di Tasso?",
      "retro": "Gerusalemme Liberata (1581)",
      "materia": "italiano",
      "categoria": "Tasso",
      "difficolta": 1,
      "intervallo": 1,
      "ripetizioni": 0,
      "facilita": 2.5,
      "prossimaRevisione": "2025-12-15T11:32:50.071Z"
    },
    {
      "id": "italiano-26",
      "fronte": "Di cosa parla la Gerusalemme Liberata?",
      "retro": "Prima crociata e conquista di Gerusalemme",
      "materia": "italiano",
      "categoria": "Tasso",
      "difficolta": 2,
      "intervallo": 1,
      "ripetizioni": 0,
      "facilita": 2.5,
      "prossimaRevisione": "2025-12-15T11:32:50.071Z"
    },
    {
      "id": "italiano-27",
      "fronte": "Chi scrisse \"La locandiera\"?",
      "retro": "Carlo Goldoni (1753)",
      "materia": "italiano",
      "categoria": "Illuminismo",
      "difficolta": 1,
      "intervallo": 1,
      "ripetizioni": 0,
      "facilita": 2.5,
      "prossimaRevisione": "2025-12-15T11:32:50.071Z"
    },
    {
      "id": "italiano-28",
      "fronte": "Cos'è \"Il Giorno\" di Parini?",
      "retro": "Poemetto satirico sulla nobiltà milanese",
      "materia": "italiano",
      "categoria": "Illuminismo",
      "difficolta": 2,
      "intervallo": 1,
      "ripetizioni": 0,
      "facilita": 2.5,
      "prossimaRevisione": "2025-12-15T11:32:50.071Z"
    },
    {
      "id": "italiano-29",
      "fronte": "Quali sono le tragedie principali di Alfieri?",
      "retro": "Saul, Mirra",
      "materia": "italiano",
      "categoria": "Illuminismo",
      "difficolta": 2,
      "intervallo": 1,
      "ripetizioni": 0,
      "facilita": 2.5,
      "prossimaRevisione": "2025-12-15T11:32:50.071Z"
    },
    {
      "id": "italiano-30",
      "fronte": "Quando nacque Ugo Foscolo?",
      "retro": "1778 a Zante (Grecia)",
      "materia": "italiano",
      "categoria": "Foscolo",
      "difficolta": 1,
      "intervallo": 1,
      "ripetizioni": 0,
      "facilita": 2.5,
      "prossimaRevisione": "2025-12-15T11:32:50.071Z"
    },
    {
      "id": "italiano-31",
      "fronte": "Qual è l'opera principale di Foscolo?",
      "retro": "I Sepolcri (1807)",
      "materia": "italiano",
      "categoria": "Foscolo",
      "difficolta": 1,
      "intervallo": 1,
      "ripetizioni": 0,
      "facilita": 2.5,
      "prossimaRevisione": "2025-12-15T11:32:50.071Z"
    },
    {
      "id": "italiano-32",
      "fronte": "Di cosa parlano \"I Sepolcri\"?",
      "retro": "Valore civile delle tombe, memoria dei grandi",
      "materia": "italiano",
      "categoria": "Foscolo",
      "difficolta": 2,
      "intervallo": 1,
      "ripetizioni": 0,
      "facilita": 2.5,
      "prossimaRevisione": "2025-12-15T11:32:50.071Z"
    },
    {
      "id": "italiano-33",
      "fronte": "Cos'è \"Le ultime lettere di Jacopo Ortis\"?",
      "retro": "Romanzo epistolare sul suicidio di un patriota",
      "materia": "italiano",
      "categoria": "Foscolo",
      "difficolta": 2,
      "intervallo": 1,
      "ripetizioni": 0,
      "facilita": 2.5,
      "prossimaRevisione": "2025-12-15T11:32:50.071Z"
    },
    {
      "id": "italiano-34",
      "fronte": "Quando nacque Alessandro Manzoni?",
      "retro": "1785 a Milano",
      "materia": "italiano",
      "categoria": "Manzoni",
      "difficolta": 1,
      "intervallo": 1,
      "ripetizioni": 0,
      "facilita": 2.5,
      "prossimaRevisione": "2025-12-15T11:32:50.071Z"
    },
    {
      "id": "italiano-35",
      "fronte": "Qual è l'opera principale di Manzoni?",
      "retro": "I Promessi Sposi (1827-1842)",
      "materia": "italiano",
      "categoria": "Manzoni",
      "difficolta": 1,
      "intervallo": 1,
      "ripetizioni": 0,
      "facilita": 2.5,
      "prossimaRevisione": "2025-12-15T11:32:50.071Z"
    },
    {
      "id": "italiano-36",
      "fronte": "Chi sono i protagonisti dei Promessi Sposi?",
      "retro": "Renzo Tramaglino e Lucia Mondella",
      "materia": "italiano",
      "categoria": "Manzoni",
      "difficolta": 1,
      "intervallo": 1,
      "ripetizioni": 0,
      "facilita": 2.5,
      "prossimaRevisione": "2025-12-15T11:32:50.071Z"
    },
    {
      "id": "italiano-37",
      "fronte": "In che epoca è ambientato il romanzo?",
      "retro": "Lombardia del 1628-1630, dominazione spagnola",
      "materia": "italiano",
      "categoria": "Manzoni",
      "difficolta": 2,
      "intervallo": 1,
      "ripetizioni": 0,
      "facilita": 2.5,
      "prossimaRevisione": "2025-12-15T11:32:50.071Z"
    },
    {
      "id": "italiano-38",
      "fronte": "Cos'è la \"Provvidenza\" per Manzoni?",
      "retro": "Disegno divino che guida la storia verso il bene",
      "materia": "italiano",
      "categoria": "Manzoni",
      "difficolta": 3,
      "intervallo": 1,
      "ripetizioni": 0,
      "facilita": 2.5,
      "prossimaRevisione": "2025-12-15T11:32:50.071Z"
    },
    {
      "id": "italiano-39",
      "fronte": "Chi è Don Abbondio?",
      "retro": "Il curato pavido che rifiuta di sposare Renzo e Lucia",
      "materia": "italiano",
      "categoria": "Manzoni",
      "difficolta": 1,
      "intervallo": 1,
      "ripetizioni": 0,
      "facilita": 2.5,
      "prossimaRevisione": "2025-12-15T11:32:50.071Z"
    },
    {
      "id": "italiano-40",
      "fronte": "Quando nacque Giacomo Leopardi?",
      "retro": "1798 a Recanati",
      "materia": "italiano",
      "categoria": "Leopardi",
      "difficolta": 1,
      "intervallo": 1,
      "ripetizioni": 0,
      "facilita": 2.5,
      "prossimaRevisione": "2025-12-15T11:32:50.071Z"
    },
    {
      "id": "italiano-41",
      "fronte": "Qual è l'opera poetica principale di Leopardi?",
      "retro": "I Canti",
      "materia": "italiano",
      "categoria": "Leopardi",
      "difficolta": 1,
      "intervallo": 1,
      "ripetizioni": 0,
      "facilita": 2.5,
      "prossimaRevisione": "2025-12-15T11:32:50.071Z"
    },
    {
      "id": "italiano-42",
      "fronte": "Cos'è \"L'Infinito\"?",
      "retro": "Idillio sulla contemplazione dell'infinito oltre la siepe",
      "materia": "italiano",
      "categoria": "Leopardi",
      "difficolta": 2,
      "intervallo": 1,
      "ripetizioni": 0,
      "facilita": 2.5,
      "prossimaRevisione": "2025-12-15T11:32:50.071Z"
    },
    {
      "id": "italiano-43",
      "fronte": "Cos'è il \"pessimismo cosmico\"?",
      "retro": "La natura è matrigna, indifferente alla sofferenza umana",
      "materia": "italiano",
      "categoria": "Leopardi",
      "difficolta": 3,
      "intervallo": 1,
      "ripetizioni": 0,
      "facilita": 2.5,
      "prossimaRevisione": "2025-12-15T11:32:50.071Z"
    },
    {
      "id": "italiano-44",
      "fronte": "Cosa sono le \"Operette morali\"?",
      "retro": "Prose filosofiche satiriche (dialoghi)",
      "materia": "italiano",
      "categoria": "Leopardi",
      "difficolta": 2,
      "intervallo": 1,
      "ripetizioni": 0,
      "facilita": 2.5,
      "prossimaRevisione": "2025-12-15T11:32:50.071Z"
    },
    {
      "id": "italiano-45",
      "fronte": "Cos'è lo \"Zibaldone\"?",
      "retro": "Diario di pensieri e riflessioni (1817-1832)",
      "materia": "italiano",
      "categoria": "Leopardi",
      "difficolta": 2,
      "intervallo": 1,
      "ripetizioni": 0,
      "facilita": 2.5,
      "prossimaRevisione": "2025-12-15T11:32:50.071Z"
    },
    {
      "id": "italiano-46",
      "fronte": "Quando nacque Giovanni Verga?",
      "retro": "1840 a Catania",
      "materia": "italiano",
      "categoria": "Verga",
      "difficolta": 1,
      "intervallo": 1,
      "ripetizioni": 0,
      "facilita": 2.5,
      "prossimaRevisione": "2025-12-15T11:32:50.071Z"
    },
    {
      "id": "italiano-47",
      "fronte": "Qual è l'opera principale di Verga?",
      "retro": "I Malavoglia (1881)",
      "materia": "italiano",
      "categoria": "Verga",
      "difficolta": 1,
      "intervallo": 1,
      "ripetizioni": 0,
      "facilita": 2.5,
      "prossimaRevisione": "2025-12-15T11:32:50.071Z"
    },
    {
      "id": "italiano-48",
      "fronte": "Cos'è il Verismo?",
      "retro": "Corrente che rappresenta la realtà in modo oggettivo",
      "materia": "italiano",
      "categoria": "Verga",
      "difficolta": 2,
      "intervallo": 1,
      "ripetizioni": 0,
      "facilita": 2.5,
      "prossimaRevisione": "2025-12-15T11:32:50.071Z"
    },
    {
      "id": "italiano-49",
      "fronte": "Cos'è la tecnica dell'\"impersonalità\"?",
      "retro": "L'autore scompare, la storia si racconta da sola",
      "materia": "italiano",
      "categoria": "Verga",
      "difficolta": 3,
      "intervallo": 1,
      "ripetizioni": 0,
      "facilita": 2.5,
      "prossimaRevisione": "2025-12-15T11:32:50.071Z"
    },
    {
      "id": "italiano-50",
      "fronte": "Cos'è il \"ciclo dei vinti\"?",
      "retro": "Serie di romanzi sui perdenti del progresso",
      "materia": "italiano",
      "categoria": "Verga",
      "difficolta": 2,
      "intervallo": 1,
      "ripetizioni": 0,
      "facilita": 2.5,
      "prossimaRevisione": "2025-12-15T11:32:50.071Z"
    },
    {
      "id": "italiano-51",
      "fronte": "Quando nacque Giovanni Pascoli?",
      "retro": "1855 a San Mauro di Romagna",
      "materia": "italiano",
      "categoria": "Pascoli",
      "difficolta": 1,
      "intervallo": 1,
      "ripetizioni": 0,
      "facilita": 2.5,
      "prossimaRevisione": "2025-12-15T11:32:50.071Z"
    },
    {
      "id": "italiano-52",
      "fronte": "Qual è l'opera principale di Pascoli?",
      "retro": "Myricae (1891)",
      "materia": "italiano",
      "categoria": "Pascoli",
      "difficolta": 1,
      "intervallo": 1,
      "ripetizioni": 0,
      "facilita": 2.5,
      "prossimaRevisione": "2025-12-15T11:32:50.071Z"
    },
    {
      "id": "italiano-53",
      "fronte": "Cos'è la poetica del \"fanciullino\"?",
      "retro": "Il poeta vede il mondo con stupore infantile",
      "materia": "italiano",
      "categoria": "Pascoli",
      "difficolta": 2,
      "intervallo": 1,
      "ripetizioni": 0,
      "facilita": 2.5,
      "prossimaRevisione": "2025-12-15T11:32:50.071Z"
    },
    {
      "id": "italiano-54",
      "fronte": "Cos'è il \"nido\" per Pascoli?",
      "retro": "La famiglia come rifugio dal mondo ostile",
      "materia": "italiano",
      "categoria": "Pascoli",
      "difficolta": 2,
      "intervallo": 1,
      "ripetizioni": 0,
      "facilita": 2.5,
      "prossimaRevisione": "2025-12-15T11:32:50.071Z"
    },
    {
      "id": "italiano-55",
      "fronte": "Quando nacque Gabriele D'Annunzio?",
      "retro": "1863 a Pescara",
      "materia": "italiano",
      "categoria": "D'Annunzio",
      "difficolta": 1,
      "intervallo": 1,
      "ripetizioni": 0,
      "facilita": 2.5,
      "prossimaRevisione": "2025-12-15T11:32:50.071Z"
    },
    {
      "id": "italiano-56",
      "fronte": "Qual è il romanzo principale di D'Annunzio?",
      "retro": "Il Piacere (1889)",
      "materia": "italiano",
      "categoria": "D'Annunzio",
      "difficolta": 1,
      "intervallo": 1,
      "ripetizioni": 0,
      "facilita": 2.5,
      "prossimaRevisione": "2025-12-15T11:32:50.071Z"
    },
    {
      "id": "italiano-57",
      "fronte": "Cos'è l'\"estetismo\"?",
      "retro": "Culto della bellezza come valore supremo",
      "materia": "italiano",
      "categoria": "D'Annunzio",
      "difficolta": 2,
      "intervallo": 1,
      "ripetizioni": 0,
      "facilita": 2.5,
      "prossimaRevisione": "2025-12-15T11:32:50.071Z"
    },
    {
      "id": "italiano-58",
      "fronte": "Cos'è il \"superuomo\" dannunziano?",
      "retro": "Uomo superiore che domina le masse",
      "materia": "italiano",
      "categoria": "D'Annunzio",
      "difficolta": 3,
      "intervallo": 1,
      "ripetizioni": 0,
      "facilita": 2.5,
      "prossimaRevisione": "2025-12-15T11:32:50.071Z"
    },
    {
      "id": "italiano-59",
      "fronte": "Quando nacque Luigi Pirandello?",
      "retro": "1867 ad Agrigento",
      "materia": "italiano",
      "categoria": "Pirandello",
      "difficolta": 1,
      "intervallo": 1,
      "ripetizioni": 0,
      "facilita": 2.5,
      "prossimaRevisione": "2025-12-15T11:32:50.071Z"
    },
    {
      "id": "italiano-60",
      "fronte": "Qual è il romanzo principale di Pirandello?",
      "retro": "Il fu Mattia Pascal (1904)",
      "materia": "italiano",
      "categoria": "Pirandello",
      "difficolta": 1,
      "intervallo": 1,
      "ripetizioni": 0,
      "facilita": 2.5,
      "prossimaRevisione": "2025-12-15T11:32:50.071Z"
    },
    {
      "id": "italiano-61",
      "fronte": "Cos'è la \"maschera\" per Pirandello?",
      "retro": "Ruolo sociale che nasconde il vero io",
      "materia": "italiano",
      "categoria": "Pirandello",
      "difficolta": 2,
      "intervallo": 1,
      "ripetizioni": 0,
      "facilita": 2.5,
      "prossimaRevisione": "2025-12-15T11:32:50.071Z"
    },
    {
      "id": "italiano-62",
      "fronte": "Cos'è \"Sei personaggi in cerca d'autore\"?",
      "retro": "Opera teatrale metanarrativa (1921)",
      "materia": "italiano",
      "categoria": "Pirandello",
      "difficolta": 2,
      "intervallo": 1,
      "ripetizioni": 0,
      "facilita": 2.5,
      "prossimaRevisione": "2025-12-15T11:32:50.071Z"
    },
    {
      "id": "italiano-63",
      "fronte": "Cos'è l'\"umorismo\" pirandelliano?",
      "retro": "Sentimento del contrario: riso che diventa riflessione",
      "materia": "italiano",
      "categoria": "Pirandello",
      "difficolta": 3,
      "intervallo": 1,
      "ripetizioni": 0,
      "facilita": 2.5,
      "prossimaRevisione": "2025-12-15T11:32:50.071Z"
    },
    {
      "id": "italiano-64",
      "fronte": "Quando nacque Italo Svevo?",
      "retro": "1861 a Trieste",
      "materia": "italiano",
      "categoria": "Svevo",
      "difficolta": 1,
      "intervallo": 1,
      "ripetizioni": 0,
      "facilita": 2.5,
      "prossimaRevisione": "2025-12-15T11:32:50.071Z"
    },
    {
      "id": "italiano-65",
      "fronte": "Qual è l'opera principale di Svevo?",
      "retro": "La coscienza di Zeno (1923)",
      "materia": "italiano",
      "categoria": "Svevo",
      "difficolta": 1,
      "intervallo": 1,
      "ripetizioni": 0,
      "facilita": 2.5,
      "prossimaRevisione": "2025-12-15T11:32:50.071Z"
    },
    {
      "id": "italiano-66",
      "fronte": "Cos'è l'\"inettitudine\"?",
      "retro": "Incapacità di agire e adattarsi alla vita",
      "materia": "italiano",
      "categoria": "Svevo",
      "difficolta": 2,
      "intervallo": 1,
      "ripetizioni": 0,
      "facilita": 2.5,
      "prossimaRevisione": "2025-12-15T11:32:50.071Z"
    },
    {
      "id": "italiano-67",
      "fronte": "Che ruolo ha la psicoanalisi in Svevo?",
      "retro": "Influenza di Freud nell'analisi dell'inconscio",
      "materia": "italiano",
      "categoria": "Svevo",
      "difficolta": 3,
      "intervallo": 1,
      "ripetizioni": 0,
      "facilita": 2.5,
      "prossimaRevisione": "2025-12-15T11:32:50.071Z"
    },
    {
      "id": "italiano-68",
      "fronte": "Quando nacque Giuseppe Ungaretti?",
      "retro": "1888 ad Alessandria d'Egitto",
      "materia": "italiano",
      "categoria": "Ungaretti",
      "difficolta": 1,
      "intervallo": 1,
      "ripetizioni": 0,
      "facilita": 2.5,
      "prossimaRevisione": "2025-12-15T11:32:50.071Z"
    },
    {
      "id": "italiano-69",
      "fronte": "Qual è l'opera principale di Ungaretti?",
      "retro": "L'Allegria (1931)",
      "materia": "italiano",
      "categoria": "Ungaretti",
      "difficolta": 1,
      "intervallo": 1,
      "ripetizioni": 0,
      "facilita": 2.5,
      "prossimaRevisione": "2025-12-15T11:32:50.071Z"
    },
    {
      "id": "italiano-70",
      "fronte": "Cosa significa \"M'illumino d'immenso\"?",
      "retro": "Illuminazione improvvisa di fronte all'infinito",
      "materia": "italiano",
      "categoria": "Ungaretti",
      "difficolta": 2,
      "intervallo": 1,
      "ripetizioni": 0,
      "facilita": 2.5,
      "prossimaRevisione": "2025-12-15T11:32:50.071Z"
    },
    {
      "id": "italiano-71",
      "fronte": "Cos'è l'Ermetismo?",
      "retro": "Poesia oscura, parola essenziale, analogia",
      "materia": "italiano",
      "categoria": "Ungaretti",
      "difficolta": 2,
      "intervallo": 1,
      "ripetizioni": 0,
      "facilita": 2.5,
      "prossimaRevisione": "2025-12-15T11:32:50.071Z"
    },
    {
      "id": "italiano-72",
      "fronte": "Quando nacque Eugenio Montale?",
      "retro": "1896 a Genova",
      "materia": "italiano",
      "categoria": "Montale",
      "difficolta": 1,
      "intervallo": 1,
      "ripetizioni": 0,
      "facilita": 2.5,
      "prossimaRevisione": "2025-12-15T11:32:50.071Z"
    },
    {
      "id": "italiano-73",
      "fronte": "Qual è l'opera principale di Montale?",
      "retro": "Ossi di seppia (1925)",
      "materia": "italiano",
      "categoria": "Montale",
      "difficolta": 1,
      "intervallo": 1,
      "ripetizioni": 0,
      "facilita": 2.5,
      "prossimaRevisione": "2025-12-15T11:32:50.071Z"
    },
    {
      "id": "italiano-74",
      "fronte": "Cos'è il \"male di vivere\"?",
      "retro": "Condizione esistenziale di sofferenza e aridità",
      "materia": "italiano",
      "categoria": "Montale",
      "difficolta": 2,
      "intervallo": 1,
      "ripetizioni": 0,
      "facilita": 2.5,
      "prossimaRevisione": "2025-12-15T11:32:50.071Z"
    },
    {
      "id": "italiano-75",
      "fronte": "Cos'è il \"correlativo oggettivo\"?",
      "retro": "Oggetto che esprime uno stato d'animo",
      "materia": "italiano",
      "categoria": "Montale",
      "difficolta": 3,
      "intervallo": 1,
      "ripetizioni": 0,
      "facilita": 2.5,
      "prossimaRevisione": "2025-12-15T11:32:50.071Z"
    },
    {
      "id": "italiano-76",
      "fronte": "Quando nacque Italo Calvino?",
      "retro": "1923 a Santiago de Las Vegas (Cuba)",
      "materia": "italiano",
      "categoria": "Calvino",
      "difficolta": 1,
      "intervallo": 1,
      "ripetizioni": 0,
      "facilita": 2.5,
      "prossimaRevisione": "2025-12-15T11:32:50.071Z"
    },
    {
      "id": "italiano-77",
      "fronte": "Quali sono le opere principali di Calvino?",
      "retro": "Il barone rampante, Se una notte d'inverno un viaggiatore",
      "materia": "italiano",
      "categoria": "Calvino",
      "difficolta": 1,
      "intervallo": 1,
      "ripetizioni": 0,
      "facilita": 2.5,
      "prossimaRevisione": "2025-12-15T11:32:50.071Z"
    },
    {
      "id": "italiano-78",
      "fronte": "Cos'è la \"leggerezza\" per Calvino?",
      "retro": "Valore letterario: sottrazione di peso alla narrazione",
      "materia": "italiano",
      "categoria": "Calvino",
      "difficolta": 3,
      "intervallo": 1,
      "ripetizioni": 0,
      "facilita": 2.5,
      "prossimaRevisione": "2025-12-15T11:32:50.071Z"
    },
    {
      "id": "filosofia-1",
      "fronte": "Qual è il metodo di Socrate?",
      "retro": "Maieutica: far \"partorire\" la verità attraverso domande",
      "materia": "filosofia",
      "categoria": "Socrate",
      "difficolta": 2,
      "intervallo": 1,
      "ripetizioni": 0,
      "facilita": 2.5,
      "prossimaRevisione": "2025-12-15T11:32:50.072Z"
    },
    {
      "id": "filosofia-2",
      "fronte": "Cosa significa \"So di non sapere\"?",
      "retro": "Consapevolezza dei propri limiti, inizio della saggezza",
      "materia": "filosofia",
      "categoria": "Socrate",
      "difficolta": 2,
      "intervallo": 1,
      "ripetizioni": 0,
      "facilita": 2.5,
      "prossimaRevisione": "2025-12-15T11:32:50.072Z"
    },
    {
      "id": "filosofia-3",
      "fronte": "Cos'è l'ironia socratica?",
      "retro": "Fingere ignoranza per smascherare la falsa sapienza",
      "materia": "filosofia",
      "categoria": "Socrate",
      "difficolta": 2,
      "intervallo": 1,
      "ripetizioni": 0,
      "facilita": 2.5,
      "prossimaRevisione": "2025-12-15T11:32:50.072Z"
    },
    {
      "id": "filosofia-4",
      "fronte": "Cos'è la teoria delle Idee?",
      "retro": "Le Idee sono modelli perfetti ed eterni delle cose sensibili",
      "materia": "filosofia",
      "categoria": "Platone",
      "difficolta": 2,
      "intervallo": 1,
      "ripetizioni": 0,
      "facilita": 2.5,
      "prossimaRevisione": "2025-12-15T11:32:50.072Z"
    },
    {
      "id": "filosofia-5",
      "fronte": "Cos'è il mito della caverna?",
      "retro": "Allegoria: prigionieri vedono ombre, il filosofo esce alla luce",
      "materia": "filosofia",
      "categoria": "Platone",
      "difficolta": 2,
      "intervallo": 1,
      "ripetizioni": 0,
      "facilita": 2.5,
      "prossimaRevisione": "2025-12-15T11:32:50.072Z"
    },
    {
      "id": "filosofia-6",
      "fronte": "Cos'è l'Iperuranio?",
      "retro": "Luogo sopraceleste dove risiedono le Idee",
      "materia": "filosofia",
      "categoria": "Platone",
      "difficolta": 2,
      "intervallo": 1,
      "ripetizioni": 0,
      "facilita": 2.5,
      "prossimaRevisione": "2025-12-15T11:32:50.072Z"
    },
    {
      "id": "filosofia-7",
      "fronte": "Quali sono le parti dell'anima per Platone?",
      "retro": "Razionale (testa), irascibile (petto), concupiscibile (ventre)",
      "materia": "filosofia",
      "categoria": "Platone",
      "difficolta": 3,
      "intervallo": 1,
      "ripetizioni": 0,
      "facilita": 2.5,
      "prossimaRevisione": "2025-12-15T11:32:50.072Z"
    },
    {
      "id": "filosofia-8",
      "fronte": "Cosa sono potenza e atto?",
      "retro": "Potenza: possibilità; Atto: realizzazione",
      "materia": "filosofia",
      "categoria": "Aristotele",
      "difficolta": 2,
      "intervallo": 1,
      "ripetizioni": 0,
      "facilita": 2.5,
      "prossimaRevisione": "2025-12-15T11:32:50.072Z"
    },
    {
      "id": "filosofia-9",
      "fronte": "Quali sono le quattro cause?",
      "retro": "Materiale, formale, efficiente, finale",
      "materia": "filosofia",
      "categoria": "Aristotele",
      "difficolta": 2,
      "intervallo": 1,
      "ripetizioni": 0,
      "facilita": 2.5,
      "prossimaRevisione": "2025-12-15T11:32:50.072Z"
    },
    {
      "id": "filosofia-10",
      "fronte": "Cos'è l'eudaimonia?",
      "retro": "Felicità come realizzazione delle proprie potenzialità",
      "materia": "filosofia",
      "categoria": "Aristotele",
      "difficolta": 2,
      "intervallo": 1,
      "ripetizioni": 0,
      "facilita": 2.5,
      "prossimaRevisione": "2025-12-15T11:32:50.072Z"
    },
    {
      "id": "filosofia-11",
      "fronte": "Cos'è il sillogismo?",
      "retro": "Ragionamento deduttivo: premessa maggiore + minore = conclusione",
      "materia": "filosofia",
      "categoria": "Aristotele",
      "difficolta": 3,
      "intervallo": 1,
      "ripetizioni": 0,
      "facilita": 2.5,
      "prossimaRevisione": "2025-12-15T11:32:50.072Z"
    },
    {
      "id": "filosofia-12",
      "fronte": "Cosa significa \"Cogito ergo sum\"?",
      "retro": "Penso dunque sono: certezza indubitabile dell'io pensante",
      "materia": "filosofia",
      "categoria": "Cartesio",
      "difficolta": 1,
      "intervallo": 1,
      "ripetizioni": 0,
      "facilita": 2.5,
      "prossimaRevisione": "2025-12-15T11:32:50.072Z"
    },
    {
      "id": "filosofia-13",
      "fronte": "Cos'è il dubbio metodico?",
      "retro": "Mettere in dubbio tutto per trovare certezze indubitabili",
      "materia": "filosofia",
      "categoria": "Cartesio",
      "difficolta": 2,
      "intervallo": 1,
      "ripetizioni": 0,
      "facilita": 2.5,
      "prossimaRevisione": "2025-12-15T11:32:50.072Z"
    },
    {
      "id": "filosofia-14",
      "fronte": "Cosa sono res cogitans e res extensa?",
      "retro": "Sostanza pensante (mente) e sostanza estesa (corpo)",
      "materia": "filosofia",
      "categoria": "Cartesio",
      "difficolta": 2,
      "intervallo": 1,
      "ripetizioni": 0,
      "facilita": 2.5,
      "prossimaRevisione": "2025-12-15T11:32:50.072Z"
    },
    {
      "id": "filosofia-15",
      "fronte": "Cos'è la \"rivoluzione copernicana\" di Kant?",
      "retro": "Non la mente si adatta agli oggetti, ma gli oggetti alla mente",
      "materia": "filosofia",
      "categoria": "Kant",
      "difficolta": 3,
      "intervallo": 1,
      "ripetizioni": 0,
      "facilita": 2.5,
      "prossimaRevisione": "2025-12-15T11:32:50.072Z"
    },
    {
      "id": "filosofia-16",
      "fronte": "Cosa sono fenomeno e noumeno?",
      "retro": "Fenomeno: cosa come appare; Noumeno: cosa in sé, inconoscibile",
      "materia": "filosofia",
      "categoria": "Kant",
      "difficolta": 2,
      "intervallo": 1,
      "ripetizioni": 0,
      "facilita": 2.5,
      "prossimaRevisione": "2025-12-15T11:32:50.072Z"
    },
    {
      "id": "filosofia-17",
      "fronte": "Cos'è l'imperativo categorico?",
      "retro": "Agisci secondo una massima che possa diventare legge universale",
      "materia": "filosofia",
      "categoria": "Kant",
      "difficolta": 2,
      "intervallo": 1,
      "ripetizioni": 0,
      "facilita": 2.5,
      "prossimaRevisione": "2025-12-15T11:32:50.072Z"
    },
    {
      "id": "filosofia-18",
      "fronte": "Cosa sono i giudizi sintetici a priori?",
      "retro": "Giudizi che ampliano la conoscenza ma sono universali e necessari",
      "materia": "filosofia",
      "categoria": "Kant",
      "difficolta": 3,
      "intervallo": 1,
      "ripetizioni": 0,
      "facilita": 2.5,
      "prossimaRevisione": "2025-12-15T11:32:50.072Z"
    },
    {
      "id": "filosofia-19",
      "fronte": "Cos'è la dialettica hegeliana?",
      "retro": "Tesi + Antitesi = Sintesi (superamento delle contraddizioni)",
      "materia": "filosofia",
      "categoria": "Hegel",
      "difficolta": 2,
      "intervallo": 1,
      "ripetizioni": 0,
      "facilita": 2.5,
      "prossimaRevisione": "2025-12-15T11:32:50.072Z"
    },
    {
      "id": "filosofia-20",
      "fronte": "Cosa significa \"Ciò che è razionale è reale\"?",
      "retro": "La realtà è manifestazione della Ragione/Spirito",
      "materia": "filosofia",
      "categoria": "Hegel",
      "difficolta": 3,
      "intervallo": 1,
      "ripetizioni": 0,
      "facilita": 2.5,
      "prossimaRevisione": "2025-12-15T11:32:50.072Z"
    },
    {
      "id": "filosofia-21",
      "fronte": "Cos'è lo Spirito Assoluto?",
      "retro": "La totalità del reale che si realizza attraverso arte, religione, filosofia",
      "materia": "filosofia",
      "categoria": "Hegel",
      "difficolta": 3,
      "intervallo": 1,
      "ripetizioni": 0,
      "facilita": 2.5,
      "prossimaRevisione": "2025-12-15T11:32:50.072Z"
    },
    {
      "id": "filosofia-22",
      "fronte": "Cos'è il materialismo storico?",
      "retro": "La storia è determinata dai rapporti economici di produzione",
      "materia": "filosofia",
      "categoria": "Marx",
      "difficolta": 2,
      "intervallo": 1,
      "ripetizioni": 0,
      "facilita": 2.5,
      "prossimaRevisione": "2025-12-15T11:32:50.072Z"
    },
    {
      "id": "filosofia-23",
      "fronte": "Cos'è il plusvalore?",
      "retro": "Differenza tra valore prodotto dal lavoratore e salario ricevuto",
      "materia": "filosofia",
      "categoria": "Marx",
      "difficolta": 2,
      "intervallo": 1,
      "ripetizioni": 0,
      "facilita": 2.5,
      "prossimaRevisione": "2025-12-15T11:32:50.072Z"
    },
    {
      "id": "filosofia-24",
      "fronte": "Cos'è l'alienazione per Marx?",
      "retro": "Il lavoratore è estraneo al prodotto, al lavoro, a sé stesso",
      "materia": "filosofia",
      "categoria": "Marx",
      "difficolta": 2,
      "intervallo": 1,
      "ripetizioni": 0,
      "facilita": 2.5,
      "prossimaRevisione": "2025-12-15T11:32:50.072Z"
    },
    {
      "id": "filosofia-25",
      "fronte": "Cosa sono struttura e sovrastruttura?",
      "retro": "Struttura: economia; Sovrastruttura: politica, cultura, religione",
      "materia": "filosofia",
      "categoria": "Marx",
      "difficolta": 3,
      "intervallo": 1,
      "ripetizioni": 0,
      "facilita": 2.5,
      "prossimaRevisione": "2025-12-15T11:32:50.072Z"
    },
    {
      "id": "filosofia-26",
      "fronte": "Cosa significa \"Dio è morto\"?",
      "retro": "Crollo dei valori tradizionali, nichilismo",
      "materia": "filosofia",
      "categoria": "Nietzsche",
      "difficolta": 2,
      "intervallo": 1,
      "ripetizioni": 0,
      "facilita": 2.5,
      "prossimaRevisione": "2025-12-15T11:32:50.072Z"
    },
    {
      "id": "filosofia-27",
      "fronte": "Cos'è il superuomo (Übermensch)?",
      "retro": "Uomo che crea nuovi valori dopo la morte di Dio",
      "materia": "filosofia",
      "categoria": "Nietzsche",
      "difficolta": 2,
      "intervallo": 1,
      "ripetizioni": 0,
      "facilita": 2.5,
      "prossimaRevisione": "2025-12-15T11:32:50.072Z"
    },
    {
      "id": "filosofia-28",
      "fronte": "Cos'è l'eterno ritorno?",
      "retro": "Tutto ritorna eternamente: vivere come se ogni istante dovesse ripetersi",
      "materia": "filosofia",
      "categoria": "Nietzsche",
      "difficolta": 3,
      "intervallo": 1,
      "ripetizioni": 0,
      "facilita": 2.5,
      "prossimaRevisione": "2025-12-15T11:32:50.072Z"
    },
    {
      "id": "filosofia-29",
      "fronte": "Cos'è la volontà di potenza?",
      "retro": "Impulso fondamentale alla crescita e all'autoaffermazione",
      "materia": "filosofia",
      "categoria": "Nietzsche",
      "difficolta": 3,
      "intervallo": 1,
      "ripetizioni": 0,
      "facilita": 2.5,
      "prossimaRevisione": "2025-12-15T11:32:50.072Z"
    },
    {
      "id": "filosofia-30",
      "fronte": "Cosa significa \"l'esistenza precede l'essenza\"?",
      "retro": "L'uomo prima esiste, poi si definisce attraverso le scelte",
      "materia": "filosofia",
      "categoria": "Sartre",
      "difficolta": 2,
      "intervallo": 1,
      "ripetizioni": 0,
      "facilita": 2.5,
      "prossimaRevisione": "2025-12-15T11:32:50.072Z"
    },
    {
      "id": "filosofia-31",
      "fronte": "Cos'è la malafede per Sartre?",
      "retro": "Negare la propria libertà, fingere di non poter scegliere",
      "materia": "filosofia",
      "categoria": "Sartre",
      "difficolta": 3,
      "intervallo": 1,
      "ripetizioni": 0,
      "facilita": 2.5,
      "prossimaRevisione": "2025-12-15T11:32:50.072Z"
    },
    {
      "id": "filosofia-32",
      "fronte": "Cos'è il Dasein per Heidegger?",
      "retro": "L'esserci: l'uomo come essere-nel-mondo",
      "materia": "filosofia",
      "categoria": "Heidegger",
      "difficolta": 3,
      "intervallo": 1,
      "ripetizioni": 0,
      "facilita": 2.5,
      "prossimaRevisione": "2025-12-15T11:32:50.072Z"
    },
    {
      "id": "filosofia-33",
      "fronte": "Cos'è l'essere-per-la-morte?",
      "retro": "La morte come possibilità più propria che dà senso all'esistenza",
      "materia": "filosofia",
      "categoria": "Heidegger",
      "difficolta": 3,
      "intervallo": 1,
      "ripetizioni": 0,
      "facilita": 2.5,
      "prossimaRevisione": "2025-12-15T11:32:50.072Z"
    },
    {
      "id": "storia-1",
      "fronte": "Quando fu il Congresso di Vienna?",
      "retro": "1814-1815",
      "materia": "storia",
      "categoria": "Risorgimento",
      "difficolta": 1,
      "intervallo": 1,
      "ripetizioni": 0,
      "facilita": 2.5,
      "prossimaRevisione": "2025-12-15T11:32:50.073Z"
    },
    {
      "id": "storia-2",
      "fronte": "Cos'è la Restaurazione?",
      "retro": "Ritorno all'ordine pre-napoleonico, legittimismo",
      "materia": "storia",
      "categoria": "Risorgimento",
      "difficolta": 2,
      "intervallo": 1,
      "ripetizioni": 0,
      "facilita": 2.5,
      "prossimaRevisione": "2025-12-15T11:32:50.073Z"
    },
    {
      "id": "storia-3",
      "fronte": "Chi fondò la Giovine Italia?",
      "retro": "Giuseppe Mazzini (1831)",
      "materia": "storia",
      "categoria": "Risorgimento",
      "difficolta": 1,
      "intervallo": 1,
      "ripetizioni": 0,
      "facilita": 2.5,
      "prossimaRevisione": "2025-12-15T11:32:50.073Z"
    },
    {
      "id": "storia-4",
      "fronte": "Quando fu la Spedizione dei Mille?",
      "retro": "1860",
      "materia": "storia",
      "categoria": "Risorgimento",
      "difficolta": 1,
      "intervallo": 1,
      "ripetizioni": 0,
      "facilita": 2.5,
      "prossimaRevisione": "2025-12-15T11:32:50.073Z"
    },
    {
      "id": "storia-5",
      "fronte": "Quando fu proclamato il Regno d'Italia?",
      "retro": "17 marzo 1861",
      "materia": "storia",
      "categoria": "Risorgimento",
      "difficolta": 1,
      "intervallo": 1,
      "ripetizioni": 0,
      "facilita": 2.5,
      "prossimaRevisione": "2025-12-15T11:32:50.073Z"
    },
    {
      "id": "storia-6",
      "fronte": "Chi fu il primo re d'Italia?",
      "retro": "Vittorio Emanuele II",
      "materia": "storia",
      "categoria": "Risorgimento",
      "difficolta": 1,
      "intervallo": 1,
      "ripetizioni": 0,
      "facilita": 2.5,
      "prossimaRevisione": "2025-12-15T11:32:50.073Z"
    },
    {
      "id": "storia-7",
      "fronte": "Quando Roma divenne capitale?",
      "retro": "1871 (Breccia di Porta Pia: 1870)",
      "materia": "storia",
      "categoria": "Risorgimento",
      "difficolta": 2,
      "intervallo": 1,
      "ripetizioni": 0,
      "facilita": 2.5,
      "prossimaRevisione": "2025-12-15T11:32:50.073Z"
    },
    {
      "id": "storia-8",
      "fronte": "Quando iniziò la Prima Guerra Mondiale?",
      "retro": "28 luglio 1914",
      "materia": "storia",
      "categoria": "Prima Guerra Mondiale",
      "difficolta": 1,
      "intervallo": 1,
      "ripetizioni": 0,
      "facilita": 2.5,
      "prossimaRevisione": "2025-12-15T11:32:50.073Z"
    },
    {
      "id": "storia-9",
      "fronte": "Cosa scatenò la Prima Guerra Mondiale?",
      "retro": "Attentato di Sarajevo (28 giugno 1914)",
      "materia": "storia",
      "categoria": "Prima Guerra Mondiale",
      "difficolta": 1,
      "intervallo": 1,
      "ripetizioni": 0,
      "facilita": 2.5,
      "prossimaRevisione": "2025-12-15T11:32:50.073Z"
    },
    {
      "id": "storia-10",
      "fronte": "Quando entrò in guerra l'Italia?",
      "retro": "24 maggio 1915",
      "materia": "storia",
      "categoria": "Prima Guerra Mondiale",
      "difficolta": 1,
      "intervallo": 1,
      "ripetizioni": 0,
      "facilita": 2.5,
      "prossimaRevisione": "2025-12-15T11:32:50.073Z"
    },
    {
      "id": "storia-11",
      "fronte": "Cos'era il Patto di Londra?",
      "retro": "Accordo segreto (1915) per l'entrata in guerra dell'Italia",
      "materia": "storia",
      "categoria": "Prima Guerra Mondiale",
      "difficolta": 2,
      "intervallo": 1,
      "ripetizioni": 0,
      "facilita": 2.5,
      "prossimaRevisione": "2025-12-15T11:32:50.073Z"
    },
    {
      "id": "storia-12",
      "fronte": "Quando fu la disfatta di Caporetto?",
      "retro": "24 ottobre 1917",
      "materia": "storia",
      "categoria": "Prima Guerra Mondiale",
      "difficolta": 2,
      "intervallo": 1,
      "ripetizioni": 0,
      "facilita": 2.5,
      "prossimaRevisione": "2025-12-15T11:32:50.073Z"
    },
    {
      "id": "storia-13",
      "fronte": "Quando finì la Prima Guerra Mondiale?",
      "retro": "11 novembre 1918",
      "materia": "storia",
      "categoria": "Prima Guerra Mondiale",
      "difficolta": 1,
      "intervallo": 1,
      "ripetizioni": 0,
      "facilita": 2.5,
      "prossimaRevisione": "2025-12-15T11:32:50.073Z"
    },
    {
      "id": "storia-14",
      "fronte": "Quando fu la Marcia su Roma?",
      "retro": "28 ottobre 1922",
      "materia": "storia",
      "categoria": "Fascismo",
      "difficolta": 1,
      "intervallo": 1,
      "ripetizioni": 0,
      "facilita": 2.5,
      "prossimaRevisione": "2025-12-15T11:32:50.073Z"
    },
    {
      "id": "storia-15",
      "fronte": "Quando furono le leggi fascistissime?",
      "retro": "1925-1926",
      "materia": "storia",
      "categoria": "Fascismo",
      "difficolta": 2,
      "intervallo": 1,
      "ripetizioni": 0,
      "facilita": 2.5,
      "prossimaRevisione": "2025-12-15T11:32:50.073Z"
    },
    {
      "id": "storia-16",
      "fronte": "Quando furono i Patti Lateranensi?",
      "retro": "11 febbraio 1929",
      "materia": "storia",
      "categoria": "Fascismo",
      "difficolta": 2,
      "intervallo": 1,
      "ripetizioni": 0,
      "facilita": 2.5,
      "prossimaRevisione": "2025-12-15T11:32:50.073Z"
    },
    {
      "id": "storia-17",
      "fronte": "Quando furono le leggi razziali?",
      "retro": "1938",
      "materia": "storia",
      "categoria": "Fascismo",
      "difficolta": 1,
      "intervallo": 1,
      "ripetizioni": 0,
      "facilita": 2.5,
      "prossimaRevisione": "2025-12-15T11:32:50.073Z"
    },
    {
      "id": "storia-18",
      "fronte": "Quando iniziò la Seconda Guerra Mondiale?",
      "retro": "1 settembre 1939",
      "materia": "storia",
      "categoria": "Seconda Guerra Mondiale",
      "difficolta": 1,
      "intervallo": 1,
      "ripetizioni": 0,
      "facilita": 2.5,
      "prossimaRevisione": "2025-12-15T11:32:50.073Z"
    },
    {
      "id": "storia-19",
      "fronte": "Quando entrò in guerra l'Italia?",
      "retro": "10 giugno 1940",
      "materia": "storia",
      "categoria": "Seconda Guerra Mondiale",
      "difficolta": 1,
      "intervallo": 1,
      "ripetizioni": 0,
      "facilita": 2.5,
      "prossimaRevisione": "2025-12-15T11:32:50.073Z"
    },
    {
      "id": "storia-20",
      "fronte": "Quando fu l'armistizio italiano?",
      "retro": "8 settembre 1943",
      "materia": "storia",
      "categoria": "Seconda Guerra Mondiale",
      "difficolta": 1,
      "intervallo": 1,
      "ripetizioni": 0,
      "facilita": 2.5,
      "prossimaRevisione": "2025-12-15T11:32:50.073Z"
    },
    {
      "id": "storia-21",
      "fronte": "Quando fu la Liberazione?",
      "retro": "25 aprile 1945",
      "materia": "storia",
      "categoria": "Seconda Guerra Mondiale",
      "difficolta": 1,
      "intervallo": 1,
      "ripetizioni": 0,
      "facilita": 2.5,
      "prossimaRevisione": "2025-12-15T11:32:50.073Z"
    },
    {
      "id": "storia-22",
      "fronte": "Quando finì la Seconda Guerra Mondiale in Europa?",
      "retro": "8 maggio 1945",
      "materia": "storia",
      "categoria": "Seconda Guerra Mondiale",
      "difficolta": 1,
      "intervallo": 1,
      "ripetizioni": 0,
      "facilita": 2.5,
      "prossimaRevisione": "2025-12-15T11:32:50.073Z"
    },
    {
      "id": "storia-23",
      "fronte": "Quando fu il referendum Repubblica/Monarchia?",
      "retro": "2 giugno 1946",
      "materia": "storia",
      "categoria": "Repubblica",
      "difficolta": 1,
      "intervallo": 1,
      "ripetizioni": 0,
      "facilita": 2.5,
      "prossimaRevisione": "2025-12-15T11:32:50.073Z"
    },
    {
      "id": "storia-24",
      "fronte": "Quando entrò in vigore la Costituzione?",
      "retro": "1 gennaio 1948",
      "materia": "storia",
      "categoria": "Repubblica",
      "difficolta": 1,
      "intervallo": 1,
      "ripetizioni": 0,
      "facilita": 2.5,
      "prossimaRevisione": "2025-12-15T11:32:50.073Z"
    },
    {
      "id": "matematica-1",
      "fronte": "Formula risolutiva equazione di 2° grado",
      "retro": "x = (-b ± √Δ) / 2a, dove Δ = b² - 4ac",
      "materia": "matematica",
      "categoria": "Algebra",
      "difficolta": 1,
      "intervallo": 1,
      "ripetizioni": 0,
      "facilita": 2.5,
      "prossimaRevisione": "2025-12-15T11:32:50.073Z"
    },
    {
      "id": "matematica-2",
      "fronte": "Prodotto notevole (a+b)²",
      "retro": "a² + 2ab + b²",
      "materia": "matematica",
      "categoria": "Algebra",
      "difficolta": 1,
      "intervallo": 1,
      "ripetizioni": 0,
      "facilita": 2.5,
      "prossimaRevisione": "2025-12-15T11:32:50.073Z"
    },
    {
      "id": "matematica-3",
      "fronte": "Prodotto notevole (a-b)²",
      "retro": "a² - 2ab + b²",
      "materia": "matematica",
      "categoria": "Algebra",
      "difficolta": 1,
      "intervallo": 1,
      "ripetizioni": 0,
      "facilita": 2.5,
      "prossimaRevisione": "2025-12-15T11:32:50.073Z"
    },
    {
      "id": "matematica-4",
      "fronte": "Prodotto notevole (a+b)(a-b)",
      "retro": "a² - b²",
      "materia": "matematica",
      "categoria": "Algebra",
      "difficolta": 1,
      "intervallo": 1,
      "ripetizioni": 0,
      "facilita": 2.5,
      "prossimaRevisione": "2025-12-15T11:32:50.073Z"
    },
    {
      "id": "matematica-5",
      "fronte": "Teorema di Pitagora",
      "retro": "a² + b² = c² (cateti e ipotenusa)",
      "materia": "matematica",
      "categoria": "Geometria",
      "difficolta": 1,
      "intervallo": 1,
      "ripetizioni": 0,
      "facilita": 2.5,
      "prossimaRevisione": "2025-12-15T11:32:50.073Z"
    },
    {
      "id": "matematica-6",
      "fronte": "Area del cerchio",
      "retro": "A = πr²",
      "materia": "matematica",
      "categoria": "Geometria",
      "difficolta": 1,
      "intervallo": 1,
      "ripetizioni": 0,
      "facilita": 2.5,
      "prossimaRevisione": "2025-12-15T11:32:50.073Z"
    },
    {
      "id": "matematica-7",
      "fronte": "Circonferenza",
      "retro": "C = 2πr",
      "materia": "matematica",
      "categoria": "Geometria",
      "difficolta": 1,
      "intervallo": 1,
      "ripetizioni": 0,
      "facilita": 2.5,
      "prossimaRevisione": "2025-12-15T11:32:50.073Z"
    },
    {
      "id": "matematica-8",
      "fronte": "Volume della sfera",
      "retro": "V = (4/3)πr³",
      "materia": "matematica",
      "categoria": "Geometria",
      "difficolta": 2,
      "intervallo": 1,
      "ripetizioni": 0,
      "facilita": 2.5,
      "prossimaRevisione": "2025-12-15T11:32:50.073Z"
    },
    {
      "id": "matematica-9",
      "fronte": "Derivata di xⁿ",
      "retro": "nxⁿ⁻¹",
      "materia": "matematica",
      "categoria": "Analisi",
      "difficolta": 2,
      "intervallo": 1,
      "ripetizioni": 0,
      "facilita": 2.5,
      "prossimaRevisione": "2025-12-15T11:32:50.073Z"
    },
    {
      "id": "matematica-10",
      "fronte": "Derivata di sin(x)",
      "retro": "cos(x)",
      "materia": "matematica",
      "categoria": "Analisi",
      "difficolta": 2,
      "intervallo": 1,
      "ripetizioni": 0,
      "facilita": 2.5,
      "prossimaRevisione": "2025-12-15T11:32:50.073Z"
    },
    {
      "id": "matematica-11",
      "fronte": "Derivata di cos(x)",
      "retro": "-sin(x)",
      "materia": "matematica",
      "categoria": "Analisi",
      "difficolta": 2,
      "intervallo": 1,
      "ripetizioni": 0,
      "facilita": 2.5,
      "prossimaRevisione": "2025-12-15T11:32:50.073Z"
    },
    {
      "id": "matematica-12",
      "fronte": "Derivata di eˣ",
      "retro": "eˣ",
      "materia": "matematica",
      "categoria": "Analisi",
      "difficolta": 2,
      "intervallo": 1,
      "ripetizioni": 0,
      "facilita": 2.5,
      "prossimaRevisione": "2025-12-15T11:32:50.073Z"
    },
    {
      "id": "matematica-13",
      "fronte": "Derivata di ln(x)",
      "retro": "1/x",
      "materia": "matematica",
      "categoria": "Analisi",
      "difficolta": 2,
      "intervallo": 1,
      "ripetizioni": 0,
      "facilita": 2.5,
      "prossimaRevisione": "2025-12-15T11:32:50.073Z"
    },
    {
      "id": "matematica-14",
      "fronte": "sin(30°)",
      "retro": "1/2",
      "materia": "matematica",
      "categoria": "Trigonometria",
      "difficolta": 1,
      "intervallo": 1,
      "ripetizioni": 0,
      "facilita": 2.5,
      "prossimaRevisione": "2025-12-15T11:32:50.073Z"
    },
    {
      "id": "matematica-15",
      "fronte": "cos(60°)",
      "retro": "1/2",
      "materia": "matematica",
      "categoria": "Trigonometria",
      "difficolta": 1,
      "intervallo": 1,
      "ripetizioni": 0,
      "facilita": 2.5,
      "prossimaRevisione": "2025-12-15T11:32:50.073Z"
    },
    {
      "id": "matematica-16",
      "fronte": "sin(45°)",
      "retro": "√2/2",
      "materia": "matematica",
      "categoria": "Trigonometria",
      "difficolta": 1,
      "intervallo": 1,
      "ripetizioni": 0,
      "facilita": 2.5,
      "prossimaRevisione": "2025-12-15T11:32:50.073Z"
    },
    {
      "id": "matematica-17",
      "fronte": "Identità fondamentale trigonometria",
      "retro": "sin²x + cos²x = 1",
      "materia": "matematica",
      "categoria": "Trigonometria",
      "difficolta": 2,
      "intervallo": 1,
      "ripetizioni": 0,
      "facilita": 2.5,
      "prossimaRevisione": "2025-12-15T11:32:50.073Z"
    },
    {
      "id": "fisica-1",
      "fronte": "Seconda legge di Newton",
      "retro": "F = ma (forza = massa × accelerazione)",
      "materia": "fisica",
      "categoria": "Meccanica",
      "difficolta": 1,
      "intervallo": 1,
      "ripetizioni": 0,
      "facilita": 2.5,
      "prossimaRevisione": "2025-12-15T11:32:50.074Z"
    },
    {
      "id": "fisica-2",
      "fronte": "Energia cinetica",
      "retro": "Ec = ½mv²",
      "materia": "fisica",
      "categoria": "Meccanica",
      "difficolta": 1,
      "intervallo": 1,
      "ripetizioni": 0,
      "facilita": 2.5,
      "prossimaRevisione": "2025-12-15T11:32:50.074Z"
    },
    {
      "id": "fisica-3",
      "fronte": "Energia potenziale gravitazionale",
      "retro": "Ep = mgh",
      "materia": "fisica",
      "categoria": "Meccanica",
      "difficolta": 1,
      "intervallo": 1,
      "ripetizioni": 0,
      "facilita": 2.5,
      "prossimaRevisione": "2025-12-15T11:32:50.074Z"
    },
    {
      "id": "fisica-4",
      "fronte": "Legge di gravitazione universale",
      "retro": "F = Gm₁m₂/r²",
      "materia": "fisica",
      "categoria": "Gravitazione",
      "difficolta": 2,
      "intervallo": 1,
      "ripetizioni": 0,
      "facilita": 2.5,
      "prossimaRevisione": "2025-12-15T11:32:50.074Z"
    },
    {
      "id": "fisica-5",
      "fronte": "Legge di Ohm",
      "retro": "V = IR (tensione = corrente × resistenza)",
      "materia": "fisica",
      "categoria": "Elettricità",
      "difficolta": 1,
      "intervallo": 1,
      "ripetizioni": 0,
      "facilita": 2.5,
      "prossimaRevisione": "2025-12-15T11:32:50.074Z"
    },
    {
      "id": "fisica-6",
      "fronte": "Potenza elettrica",
      "retro": "P = VI",
      "materia": "fisica",
      "categoria": "Elettricità",
      "difficolta": 1,
      "intervallo": 1,
      "ripetizioni": 0,
      "facilita": 2.5,
      "prossimaRevisione": "2025-12-15T11:32:50.074Z"
    },
    {
      "id": "fisica-7",
      "fronte": "Legge di Coulomb",
      "retro": "F = kq₁q₂/r²",
      "materia": "fisica",
      "categoria": "Elettricità",
      "difficolta": 2,
      "intervallo": 1,
      "ripetizioni": 0,
      "facilita": 2.5,
      "prossimaRevisione": "2025-12-15T11:32:50.074Z"
    },
    {
      "id": "fisica-8",
      "fronte": "Equazione di Einstein",
      "retro": "E = mc²",
      "materia": "fisica",
      "categoria": "Relatività",
      "difficolta": 1,
      "intervallo": 1,
      "ripetizioni": 0,
      "facilita": 2.5,
      "prossimaRevisione": "2025-12-15T11:32:50.074Z"
    },
    {
      "id": "fisica-9",
      "fronte": "Legge dei gas perfetti",
      "retro": "PV = nRT",
      "materia": "fisica",
      "categoria": "Termodinamica",
      "difficolta": 2,
      "intervallo": 1,
      "ripetizioni": 0,
      "facilita": 2.5,
      "prossimaRevisione": "2025-12-15T11:32:50.074Z"
    },
    {
      "id": "fisica-10",
      "fronte": "Primo principio termodinamica",
      "retro": "ΔU = Q - L",
      "materia": "fisica",
      "categoria": "Termodinamica",
      "difficolta": 2,
      "intervallo": 1,
      "ripetizioni": 0,
      "facilita": 2.5,
      "prossimaRevisione": "2025-12-15T11:32:50.074Z"
    },
    {
      "id": "scienze-1",
      "fronte": "Funzione del DNA",
      "retro": "Conservare e trasmettere l'informazione genetica",
      "materia": "scienze",
      "categoria": "Genetica",
      "difficolta": 1,
      "intervallo": 1,
      "ripetizioni": 0,
      "facilita": 2.5,
      "prossimaRevisione": "2025-12-15T11:32:50.074Z"
    },
    {
      "id": "scienze-2",
      "fronte": "Dove avviene la fotosintesi?",
      "retro": "Nei cloroplasti",
      "materia": "scienze",
      "categoria": "Biologia",
      "difficolta": 1,
      "intervallo": 1,
      "ripetizioni": 0,
      "facilita": 2.5,
      "prossimaRevisione": "2025-12-15T11:32:50.074Z"
    },
    {
      "id": "scienze-3",
      "fronte": "Formula della fotosintesi",
      "retro": "6CO₂ + 6H₂O → C₆H₁₂O₆ + 6O₂",
      "materia": "scienze",
      "categoria": "Biologia",
      "difficolta": 2,
      "intervallo": 1,
      "ripetizioni": 0,
      "facilita": 2.5,
      "prossimaRevisione": "2025-12-15T11:32:50.074Z"
    },
    {
      "id": "scienze-4",
      "fronte": "Funzione dei mitocondri",
      "retro": "Produrre ATP (energia cellulare)",
      "materia": "scienze",
      "categoria": "Biologia",
      "difficolta": 1,
      "intervallo": 1,
      "ripetizioni": 0,
      "facilita": 2.5,
      "prossimaRevisione": "2025-12-15T11:32:50.074Z"
    },
    {
      "id": "scienze-5",
      "fronte": "Quanti cromosomi ha l'uomo?",
      "retro": "46 (23 coppie)",
      "materia": "scienze",
      "categoria": "Genetica",
      "difficolta": 1,
      "intervallo": 1,
      "ripetizioni": 0,
      "facilita": 2.5,
      "prossimaRevisione": "2025-12-15T11:32:50.074Z"
    },
    {
      "id": "scienze-6",
      "fronte": "Differenza mitosi/meiosi",
      "retro": "Mitosi: 2 cellule diploidi; Meiosi: 4 cellule aploidi",
      "materia": "scienze",
      "categoria": "Genetica",
      "difficolta": 2,
      "intervallo": 1,
      "ripetizioni": 0,
      "facilita": 2.5,
      "prossimaRevisione": "2025-12-15T11:32:50.074Z"
    },
    {
      "id": "scienze-7",
      "fronte": "Basi azotate del DNA",
      "retro": "Adenina, Timina, Citosina, Guanina (A-T, C-G)",
      "materia": "scienze",
      "categoria": "Genetica",
      "difficolta": 2,
      "intervallo": 1,
      "ripetizioni": 0,
      "facilita": 2.5,
      "prossimaRevisione": "2025-12-15T11:32:50.074Z"
    },
    {
      "id": "scienze-8",
      "fronte": "pH dell'acqua pura",
      "retro": "7 (neutro)",
      "materia": "scienze",
      "categoria": "Chimica",
      "difficolta": 1,
      "intervallo": 1,
      "ripetizioni": 0,
      "facilita": 2.5,
      "prossimaRevisione": "2025-12-15T11:32:50.074Z"
    },
    {
      "id": "scienze-9",
      "fronte": "Gas più abbondante nell'atmosfera",
      "retro": "Azoto (N₂) - circa 78%",
      "materia": "scienze",
      "categoria": "Chimica",
      "difficolta": 1,
      "intervallo": 1,
      "ripetizioni": 0,
      "facilita": 2.5,
      "prossimaRevisione": "2025-12-15T11:32:50.074Z"
    },
    {
      "id": "latino-1",
      "fronte": "Quante declinazioni ha il latino?",
      "retro": "5 declinazioni",
      "materia": "latino",
      "categoria": "Grammatica",
      "difficolta": 1,
      "intervallo": 1,
      "ripetizioni": 0,
      "facilita": 2.5,
      "prossimaRevisione": "2025-12-15T11:32:50.075Z"
    },
    {
      "id": "latino-2",
      "fronte": "Quante coniugazioni ha il latino?",
      "retro": "4 coniugazioni",
      "materia": "latino",
      "categoria": "Grammatica",
      "difficolta": 1,
      "intervallo": 1,
      "ripetizioni": 0,
      "facilita": 2.5,
      "prossimaRevisione": "2025-12-15T11:32:50.075Z"
    },
    {
      "id": "latino-3",
      "fronte": "Caso del complemento oggetto",
      "retro": "Accusativo",
      "materia": "latino",
      "categoria": "Grammatica",
      "difficolta": 1,
      "intervallo": 1,
      "ripetizioni": 0,
      "facilita": 2.5,
      "prossimaRevisione": "2025-12-15T11:32:50.075Z"
    },
    {
      "id": "latino-4",
      "fronte": "Caso del complemento di specificazione",
      "retro": "Genitivo",
      "materia": "latino",
      "categoria": "Grammatica",
      "difficolta": 1,
      "intervallo": 1,
      "ripetizioni": 0,
      "facilita": 2.5,
      "prossimaRevisione": "2025-12-15T11:32:50.075Z"
    },
    {
      "id": "latino-5",
      "fronte": "Traduzione \"Carpe diem\"",
      "retro": "Cogli l'attimo (Orazio)",
      "materia": "latino",
      "categoria": "Citazioni",
      "difficolta": 1,
      "intervallo": 1,
      "ripetizioni": 0,
      "facilita": 2.5,
      "prossimaRevisione": "2025-12-15T11:32:50.075Z"
    },
    {
      "id": "latino-6",
      "fronte": "Traduzione \"Cogito ergo sum\"",
      "retro": "Penso dunque sono (Cartesio)",
      "materia": "latino",
      "categoria": "Citazioni",
      "difficolta": 1,
      "intervallo": 1,
      "ripetizioni": 0,
      "facilita": 2.5,
      "prossimaRevisione": "2025-12-15T11:32:50.075Z"
    },
    {
      "id": "latino-7",
      "fronte": "Opera principale di Virgilio",
      "retro": "Eneide",
      "materia": "latino",
      "categoria": "Letteratura",
      "difficolta": 1,
      "intervallo": 1,
      "ripetizioni": 0,
      "facilita": 2.5,
      "prossimaRevisione": "2025-12-15T11:32:50.075Z"
    },
    {
      "id": "latino-8",
      "fronte": "Opera principale di Cicerone",
      "retro": "Catilinarie, De Oratore",
      "materia": "latino",
      "categoria": "Letteratura",
      "difficolta": 1,
      "intervallo": 1,
      "ripetizioni": 0,
      "facilita": 2.5,
      "prossimaRevisione": "2025-12-15T11:32:50.075Z"
    },
    {
      "id": "arte-1",
      "fronte": "Chi dipinse la Gioconda?",
      "retro": "Leonardo da Vinci (1503-1519)",
      "materia": "arte",
      "categoria": "Rinascimento",
      "difficolta": 1,
      "intervallo": 1,
      "ripetizioni": 0,
      "facilita": 2.5,
      "prossimaRevisione": "2025-12-15T11:32:50.075Z"
    },
    {
      "id": "arte-2",
      "fronte": "Chi scolpì il David?",
      "retro": "Michelangelo (1501-1504)",
      "materia": "arte",
      "categoria": "Rinascimento",
      "difficolta": 1,
      "intervallo": 1,
      "ripetizioni": 0,
      "facilita": 2.5,
      "prossimaRevisione": "2025-12-15T11:32:50.075Z"
    },
    {
      "id": "arte-3",
      "fronte": "Chi dipinse la Cappella Sistina?",
      "retro": "Michelangelo (1508-1512)",
      "materia": "arte",
      "categoria": "Rinascimento",
      "difficolta": 1,
      "intervallo": 1,
      "ripetizioni": 0,
      "facilita": 2.5,
      "prossimaRevisione": "2025-12-15T11:32:50.075Z"
    },
    {
      "id": "arte-4",
      "fronte": "Chi dipinse la Scuola di Atene?",
      "retro": "Raffaello (1509-1511)",
      "materia": "arte",
      "categoria": "Rinascimento",
      "difficolta": 1,
      "intervallo": 1,
      "ripetizioni": 0,
      "facilita": 2.5,
      "prossimaRevisione": "2025-12-15T11:32:50.075Z"
    },
    {
      "id": "arte-5",
      "fronte": "Caratteristica principale del Caravaggio",
      "retro": "Uso drammatico della luce (chiaroscuro)",
      "materia": "arte",
      "categoria": "Barocco",
      "difficolta": 2,
      "intervallo": 1,
      "ripetizioni": 0,
      "facilita": 2.5,
      "prossimaRevisione": "2025-12-15T11:32:50.075Z"
    },
    {
      "id": "arte-6",
      "fronte": "Chi dipinse \"Notte stellata\"?",
      "retro": "Vincent van Gogh (1889)",
      "materia": "arte",
      "categoria": "Post-impressionismo",
      "difficolta": 1,
      "intervallo": 1,
      "ripetizioni": 0,
      "facilita": 2.5,
      "prossimaRevisione": "2025-12-15T11:32:50.075Z"
    },
    {
      "id": "arte-7",
      "fronte": "Chi dipinse \"Guernica\"?",
      "retro": "Pablo Picasso (1937)",
      "materia": "arte",
      "categoria": "Cubismo",
      "difficolta": 1,
      "intervallo": 1,
      "ripetizioni": 0,
      "facilita": 2.5,
      "prossimaRevisione": "2025-12-15T11:32:50.075Z"
    },
    {
      "id": "arte-8",
      "fronte": "Cos'è l'Impressionismo?",
      "retro": "Movimento che cattura la luce e l'impressione del momento",
      "materia": "arte",
      "categoria": "Impressionismo",
      "difficolta": 2,
      "intervallo": 1,
      "ripetizioni": 0,
      "facilita": 2.5,
      "prossimaRevisione": "2025-12-15T11:32:50.075Z"
    },
    {
      "id": "inglese-1",
      "fronte": "Present Perfect structure",
      "retro": "have/has + past participle",
      "materia": "inglese",
      "categoria": "Grammar",
      "difficolta": 1,
      "intervallo": 1,
      "ripetizioni": 0,
      "facilita": 2.5,
      "prossimaRevisione": "2025-12-15T11:32:50.076Z"
    },
    {
      "id": "inglese-2",
      "fronte": "Second Conditional structure",
      "retro": "If + past simple, would + infinitive",
      "materia": "inglese",
      "categoria": "Grammar",
      "difficolta": 2,
      "intervallo": 1,
      "ripetizioni": 0,
      "facilita": 2.5,
      "prossimaRevisione": "2025-12-15T11:32:50.076Z"
    },
    {
      "id": "inglese-3",
      "fronte": "Third Conditional structure",
      "retro": "If + past perfect, would have + past participle",
      "materia": "inglese",
      "categoria": "Grammar",
      "difficolta": 2,
      "intervallo": 1,
      "ripetizioni": 0,
      "facilita": 2.5,
      "prossimaRevisione": "2025-12-15T11:32:50.076Z"
    },
    {
      "id": "inglese-4",
      "fronte": "Passive Voice structure",
      "retro": "be + past participle",
      "materia": "inglese",
      "categoria": "Grammar",
      "difficolta": 1,
      "intervallo": 1,
      "ripetizioni": 0,
      "facilita": 2.5,
      "prossimaRevisione": "2025-12-15T11:32:50.076Z"
    },
    {
      "id": "inglese-5",
      "fronte": "Who wrote \"Hamlet\"?",
      "retro": "William Shakespeare",
      "materia": "inglese",
      "categoria": "Literature",
      "difficolta": 1,
      "intervallo": 1,
      "ripetizioni": 0,
      "facilita": 2.5,
      "prossimaRevisione": "2025-12-15T11:32:50.076Z"
    },
    {
      "id": "inglese-6",
      "fronte": "Who wrote \"1984\"?",
      "retro": "George Orwell",
      "materia": "inglese",
      "categoria": "Literature",
      "difficolta": 1,
      "intervallo": 1,
      "ripetizioni": 0,
      "facilita": 2.5,
      "prossimaRevisione": "2025-12-15T11:32:50.076Z"
    },
    {
      "id": "inglese-7",
      "fronte": "Who wrote \"Pride and Prejudice\"?",
      "retro": "Jane Austen",
      "materia": "inglese",
      "categoria": "Literature",
      "difficolta": 1,
      "intervallo": 1,
      "ripetizioni": 0,
      "facilita": 2.5,
      "prossimaRevisione": "2025-12-15T11:32:50.076Z"
    },
    {
      "id": "religione-1",
      "fronte": "Quanti sono i Vangeli canonici?",
      "retro": "4 (Matteo, Marco, Luca, Giovanni)",
      "materia": "religione",
      "categoria": "Bibbia",
      "difficolta": 1,
      "intervallo": 1,
      "ripetizioni": 0,
      "facilita": 2.5,
      "prossimaRevisione": "2025-12-15T11:32:50.076Z"
    },
    {
      "id": "religione-2",
      "fronte": "Quanti sono i comandamenti?",
      "retro": "10",
      "materia": "religione",
      "categoria": "Dottrina",
      "difficolta": 1,
      "intervallo": 1,
      "ripetizioni": 0,
      "facilita": 2.5,
      "prossimaRevisione": "2025-12-15T11:32:50.076Z"
    },
    {
      "id": "religione-3",
      "fronte": "Quanti sono i sacramenti?",
      "retro": "7",
      "materia": "religione",
      "categoria": "Dottrina",
      "difficolta": 1,
      "intervallo": 1,
      "ripetizioni": 0,
      "facilita": 2.5,
      "prossimaRevisione": "2025-12-15T11:32:50.076Z"
    },
    {
      "id": "religione-4",
      "fronte": "Dove nacque Gesù?",
      "retro": "Betlemme",
      "materia": "religione",
      "categoria": "Vita di Gesù",
      "difficolta": 1,
      "intervallo": 1,
      "ripetizioni": 0,
      "facilita": 2.5,
      "prossimaRevisione": "2025-12-15T11:32:50.076Z"
    },
    {
      "id": "religione-5",
      "fronte": "Quanti sono gli apostoli?",
      "retro": "12",
      "materia": "religione",
      "categoria": "Vita di Gesù",
      "difficolta": 1,
      "intervallo": 1,
      "ripetizioni": 0,
      "facilita": 2.5,
      "prossimaRevisione": "2025-12-15T11:32:50.076Z"
    },
    {
      "id": "religione-6",
      "fronte": "Chi fu il primo Papa?",
      "retro": "San Pietro",
      "materia": "religione",
      "categoria": "Chiesa",
      "difficolta": 1,
      "intervallo": 1,
      "ripetizioni": 0,
      "facilita": 2.5,
      "prossimaRevisione": "2025-12-15T11:32:50.076Z"
    },
    {
      "id": "religione-7",
      "fronte": "Cosa celebra la Pasqua?",
      "retro": "La resurrezione di Gesù",
      "materia": "religione",
      "categoria": "Feste",
      "difficolta": 1,
      "intervallo": 1,
      "ripetizioni": 0,
      "facilita": 2.5,
      "prossimaRevisione": "2025-12-15T11:32:50.076Z"
    },
    {
      "id": "religione-8",
      "fronte": "Cosa celebra la Pentecoste?",
      "retro": "La discesa dello Spirito Santo",
      "materia": "religione",
      "categoria": "Feste",
      "difficolta": 2,
      "intervallo": 1,
      "ripetizioni": 0,
      "facilita": 2.5,
      "prossimaRevisione": "2025-12-15T11:32:50.076Z"
    }
  ]
}